README.md
setup.py
h4cktools/__init__.py
h4cktools/display.py
h4cktools/encode.py
h4cktools.egg-info/PKG-INFO
h4cktools.egg-info/SOURCES.txt
h4cktools.egg-info/dependency_links.txt
h4cktools.egg-info/requires.txt
h4cktools.egg-info/top_level.txt
h4cktools/generate/__init__.py
h4cktools/generate/code.py
h4cktools/generate/user.py
h4cktools/http/__init__.py
h4cktools/http/asyncsession.py
h4cktools/http/httpresponse.py
h4cktools/http/httpsession.py
h4cktools/parse/__init__.py
h4cktools/parse/args.py
h4cktools/parse/files.py
h4cktools/parse/http.py
h4cktools/parse/versions.py